simple_toolbelt/__init__.py
simple_toolbelt/path.py
simple_toolbelt-0.0.2.dist-info/LICENSE
simple_toolbelt-0.0.2.dist-info/METADATA
simple_toolbelt-0.0.2.dist-info/WHEEL
simple_toolbelt-0.0.2.dist-info/top_level.txt
simple_toolbelt-0.0.2.dist-info/RECORD
