Metadata-Version: 2.1
Name: simple-toolbelt
Version: 0.0.2
Summary: A growing collection of simple utilities functions for Python
Home-page: https://github.com/mbiemann/python-simple-toolbelt
Author: Marcell Biemann
Author-email: mbiemann@gmail.com
License: UNKNOWN
Project-URL: Bug Tracker, https://github.com/mbiemann/python-simple-toolbelt/issues
Platform: UNKNOWN
Classifier: Programming Language :: Python :: 3
Classifier: License :: OSI Approved :: MIT License
Classifier: Operating System :: OS Independent
Requires-Python: >=3.6
License-File: LICENSE
